purdy/__init__.py
purdy/_debug.py
purdy/content.py
purdy/lexers.py
purdy/parser.py
purdy/scribe.py
purdy/themes.py
purdy/utils.py
purdy/cmds/__init__.py
purdy/cmds/arg_helpers.py
purdy/cmds/purdy.py
purdy/cmds/subpurdy.py
purdy/renderers/__init__.py
purdy/renderers/formatter.py
purdy/renderers/html.py
purdy/renderers/plain.py
purdy/renderers/rich.py
purdy/renderers/rtf.py
purdy/renderers/textual.py
purdy/tui/__init__.py
purdy/tui/animate.py
purdy/tui/apps.py
purdy/tui/codebox.py
purdy/tui/purdybox.py
purdy/tui/style.tcss
purdy/tui/tui_content.py
purdy/tui/typewriter.py
purdy/tui/widgets.py
purdy-2.1.1.dist-info/METADATA
purdy-2.1.1.dist-info/WHEEL
purdy-2.1.1.dist-info/entry_points.txt
purdy-2.1.1.dist-info/top_level.txt
purdy-2.1.1.dist-info/RECORD
