Metadata-Version: 2.4
Name: purdy
Version: 2.1.1
Summary: Terminal based code snippet display tool
Author-email: Christopher Trudeau <ctrudeau+pypi@arsensa.com>
Project-URL: repository, https://github.com/cltrudeau/purdy
Project-URL: documentation, http://purdy.readthedocs.io/en/latest/
Classifier: Development Status :: 3 - Alpha
Classifier: Environment :: Web Environment
Classifier: Intended Audience :: Developers
Classifier: License :: OSI Approved :: MIT License
Classifier: Operating System :: OS Independent
Classifier: Programming Language :: Python :: 3.8
Classifier: Programming Language :: Python :: 3.9
Classifier: Programming Language :: Python :: 3.10
Classifier: Programming Language :: Python :: 3.11
Classifier: Programming Language :: Python :: 3.12
Classifier: Programming Language :: Python :: 3.13
Classifier: Programming Language :: Python :: 3.14
Classifier: Topic :: Software Development :: Libraries :: Application Frameworks
Classifier: Topic :: Software Development :: Libraries :: Python Modules
Requires-Python: >=3.10
Requires-Dist: argparse_formatter~=1.4
Requires-Dist: asttokens==3.0.0
Requires-Dist: Pygments~=2.19.2
Requires-Dist: textual~=6.1
Requires-Dist: textual-transitions>=0.0.3
Provides-Extra: build
Requires-Dist: build~=1.3; extra == "build"
Requires-Dist: twine~=6.2; extra == "build"
Provides-Extra: dev
Requires-Dist: coverage~=7.10; extra == "dev"
Requires-Dist: nox==2025.5.1; extra == "dev"
Requires-Dist: pudb==2025.1; extra == "dev"
Requires-Dist: pyflakes==3.4.0; extra == "dev"
Requires-Dist: Sphinx==8.2.3; extra == "dev"
Requires-Dist: sphinx-argparse==0.5.2; extra == "dev"
Requires-Dist: sphinx-rtd-theme==3.0.2; extra == "dev"
Requires-Dist: waelstow~=0.12; extra == "dev"
